Guia2/Ejercicio 2/eje1.v
module eje1 (
    input wire clk,
    input wire reset,
    input wire A,  // Cambiado a entrada
    input wire B,  // Cambiado a entrada
    output wire and1     // Salida correcta
);

    // Operación lógica para la salida
    assign and1 = A & B;

endmodule

Guia2/Ejercicio 1/eje1_tb.v
`default_nettype none
`timescale 100 ns / 10 ns

module eje1_tb();

//-- Parámetro para definir cuánto dura la simulación
parameter DURATION = 100; // Cambiá esto según lo que necesites

//-- Señales de entrada del módulo
reg clk = 0;
reg reset;
reg salida1;  // Cambiado a reg para poder asignar valores
reg salida2;  // Cambiado a reg para poder asignar valores

//-- Señales de salida del módulo
wire and1;  // Salida del módulo bajo prueba

reg [8:0] j ;
reg [8:0] i ;
//-- Instanciación del módulo bajo prueba
eje1 UUT (
    .clk(clk),
    .reset(reset),
    .A(salida1),
    .B(salida2),
    .and1(and1)
);
integer n;

//-- Bloque inicial: estímulos y configuración
initial begin
  // Archivo para almacenar la traza
  $dumpfile("eje1_tb.vcd");
  $dumpvars(0, eje1_tb);
  reset = 1;
  #1;
  reset = 0;

  // Generar estímulos para las entradas
  i = 9'b001000100;
  j = 9'b011101110;

  for (n = 0; n < 9; n = n + 1) begin
    salida1 = j[n];
    salida2 = i[n];
    #1; // Esperar un ciclo de reloj
  end

  // Finalizar simulación
  #(DURATION) $display("Fin de la simulación");
  $finish;
end

endmodule

Guia2/Ejercicio 1/eje1_tb.vcd
$date
	Sat May 10 09:06:53 2025
$end
$version
	Icarus Verilog
$end
$timescale
	1ps
$end
$scope module eje1_tb $end
$var wire 1 ! and1 $end
$var parameter 32 " DURATION $end
$var reg 1 # clk $end
$var reg 9 $ i [8:0] $end
$var reg 9 % j [8:0] $end
$var reg 1 & reset $end
$var reg 1 ' salida1 $end
$var reg 1 ( salida2 $end
$var integer 32 ) n [31:0] $end
$scope module UUT $end
$var wire 1 ' A $end
$var wire 1 ( B $end
$var wire 1 ! and1 $end
$var wire 1 # clk $end
$var wire 1 & reset $end
$upscope $end
$upscope $end
$enddefinitions $end
$comment Show the parameter values. $end
$dumpall
b1100100 "
$end
#0
$dumpvars
bx )
x(
x'
1&
bx %
bx $
0#
x!
$end
#100000
0!
0(
0'
b0 )
b11101110 %
b1000100 $
0&
#200000
1'
b1 )
#300000
1!
1(
b10 )
#400000
0!
0(
b11 )
#500000
0'
b100 )
#600000
1'
b101 )
#700000
1!
1(
b110 )
#800000
0!
0(
b111 )
#900000
0'
b1000 )
#1000000
b1001 )
