Guia2/Ejercicio 9/eje9.v
module eje9 (
    input wire clk,
    input wire reset,
    input wire A,  // Cambiado a entrada
    input wire B,  // Cambiado a entrada
    input wire C,
    input wire D,
    input wire E,
    output wire a1,
    output wire a2,
    output wire b1,
    output wire b2,
    output wire c1,
    output wire c2,
    output wire d1,
    output wire d2


);
    assign a1 = A&~B&C | ~A&B&~C | A&B&C;
    assign a2 = ~A&B&~C | A&C;
    assign b1 = (A | ~B)&(A | ~B | ~C)&(B | C | ~D)&(~A | B | ~C | D);
    assign b2 = ~B&~C&~D | A&C&D | ~A&~B&C | A&B;
    assign c1 = (A | B | C)&(~A | ~B | ~C)&(A | ~B | C);
    assign c2 =  A&~C | ~A&C | A&~B&C;
    assign d1 = ~A&B&~C&D&~E | ~A&~B&~C&D&E | A&~B&~C&D&E | A&B&~C&~D&~E | ~A&B&C&D&~E | ~A&B&C&~D&E | ~A&~B&~C&~D&~E | ~A&~B&C&D&E | A&B&~C&D&~E | A&B&~C&D&E;
    assign d2 = ~A&~B&~C&~D&~E | ~A&B&C&~D&E | A&B&~C&~E | A&B&~C&D | ~A&B&D&~E | ~B&~C&D&E | ~A&~B&D&E;
    // Operación lógica para la salida




endmodule

Guia2/Ejercicio 9/eje9_tb.v
`default_nettype none
`timescale 100 ns / 10 ns

module eje9_tb();

//-- Parámetro para definir cuánto dura la simulación
parameter DURATION = 100; // Cambiá esto según lo que necesites

//-- Señales de entrada del módulo
reg clk = 0;
reg reset;
reg A;  // Cambiado a reg para poder asignar valores
reg B;  // Cambiado a reg para poder asignar valores
reg C;
reg D;
reg E;

//-- Instanciación del módulo bajo prueba
eje9 UUT (
    .clk(clk),
    .reset(reset),
    .A(A),
    .B(B),
    .C(C),
    .D(D),
    .E(E)
);
integer n;

//-- Bloque inicial: estímulos y configuración
initial begin
  // Archivo para almacenar la traza
  $dumpfile("eje9_tb.vcd");
  $dumpvars(0, eje9_tb);
  reset = 1;
  #1;
  reset = 0;
  for (n = 0; n < 32; n = n + 1) begin
    {A,B,C,D,E}=n;
    #1; // Esperar un ciclo de reloj
  end


  // Finalizar simulación
  #(DURATION) $display("Fin de la simulación");
  $finish;
end

endmodule

Guia2/Ejercicio 9/eje9_tb.vcd
$date
	Sun May 11 15:47:15 2025
$end
$version
	Icarus Verilog
$end
$timescale
	1ps
$end
$scope module eje9_tb $end
$var parameter 32 ! DURATION $end
$var reg 1 " A $end
$var reg 1 # B $end
$var reg 1 $ C $end
$var reg 1 % D $end
$var reg 1 & E $end
$var reg 1 ' clk $end
$var reg 1 ( reset $end
$var integer 32 ) n [31:0] $end
$scope module UUT $end
$var wire 1 " A $end
$var wire 1 # B $end
$var wire 1 $ C $end
$var wire 1 % D $end
$var wire 1 & E $end
$var wire 1 * a1 $end
$var wire 1 + a2 $end
$var wire 1 , b1 $end
$var wire 1 - b2 $end
$var wire 1 . c1 $end
$var wire 1 / c2 $end
$var wire 1 ' clk $end
$var wire 1 0 d1 $end
$var wire 1 1 d2 $end
$var wire 1 ( reset $end
$upscope $end
$upscope $end
$enddefinitions $end
$comment Show the parameter values. $end
$dumpall
b1100100 !
$end
#0
$dumpvars
x1
x0
x/
x.
x-
x,
x+
x*
bx )
1(
0'
x&
x%
x$
x#
x"
$end
#100000
11
10
1-
1,
0.
0*
0+
0/
0"
0#
0$
0%
0&
b0 )
0(
#200000
01
00
1&
b1 )
#300000
01
00
0-
0,
1%
0&
b10 )
#400000
10
11
1&
b11 )
#500000
00
1,
1-
1.
1/
01
1$
0%
0&
b100 )
#600000
1&
b101 )
#700000
1%
0&
b110 )
#800000
10
11
1&
b111 )
#900000
0,
1*
00
1+
0-
0.
0/
01
1#
0$
0%
0&
b1000 )
#1000000
1&
b1001 )
#1100000
10
11
1%
0&
b1010 )
#1200000
00
01
1&
b1011 )
#1300000
0*
0+
1/
1.
1$
0%
0&
b1100 )
#1400000
11
10
1&
b1101 )
#1500000
10
1%
0&
b1110 )
#1600000
00
01
1&
b1111 )
#1700000
1-
1,
1.
1"
0#
0$
0%
0&
b10000 )
#1800000
1&
b10001 )
#1900000
0-
0,
1%
0&
b10010 )
#2000000
10
11
1&
b10011 )
#2100000
00
0-
1*
01
1+
1$
0%
0&
b10100 )
#2200000
1&
b10101 )
#2300000
1-
1,
1%
0&
b10110 )
#2400000
1&
b10111 )
#2500000
10
11
0*
0+
1/
1,
1#
0$
0%
0&
b11000 )
#2600000
00
01
1&
b11001 )
#2700000
11
10
1%
0&
b11010 )
#2800000
1&
b11011 )
#2900000
01
0.
0/
1*
1+
00
1$
0%
0&
b11100 )
#3000000
1&
b11101 )
#3100000
1%
0&
b11110 )
#3200000
1&
b11111 )
#3300000
b100000 )
