Guia3/eje3/a/ejercicio3a.v
module ejercicio3a (
    input wire clk,
    input wire reset,
    input wire [9:0] dec,  // Cambiado a entrada
    output reg [3:0] salida
);

    // Operación lógica para la salida
    always @(*) begin
        case (dec)
            10'b0000000001: salida = 4'b0000;
            10'b0000000010: salida = 4'b0001;
            10'b0000000100: salida = 4'b0010;
            10'b0000001000: salida = 4'b0011;
            10'b0000010000: salida = 4'b0100;
            10'b0000100000: salida = 4'b0101;
            10'b0001000000: salida = 4'b0110;
            10'b0010000000: salida = 4'b0111;
            10'b0100000000: salida = 4'b1000;
            10'b1000000000: salida = 4'b1001;
            10'b0000000000: salida = 4'b1111; // Valor por defecto
            default: salida = 4'bxxxx;
        endcase
    end

endmodule

Guia3/eje3/a/ejercicio3a_tb.v
`default_nettype none
`timescale 100 ns / 10 ns

module ejercicio3a_tb();

//-- Parámetro para definir cuánto dura la simulación
parameter DURATION = 100; // Cambiá esto según lo que necesites

//-- Señales de entrada del módulo
reg clk = 0;
reg reset;

reg [9:0] i ;
input wire [9:0] salida_tb;
//-- Instanciación del módulo bajo prueba
ejercicio3a UUT (
    .clk(clk),
    .reset(reset),
    .dec(i),
    .salida(salida_tb)
);

//-- Bloque inicial: estímulos y configuración
initial begin
  // Archivo para almacenar la traza
  $dumpfile("ejercicio3a_tb.vcd");
  $dumpvars(0, ejercicio3a_tb);
  reset = 1;
  #1;
  reset = 0;
  i = 10'b0000000000; // Inicializar entrada
    #1;
  i = 10'b0000000001; // Iniciar con el primer valor
    #1;
  i = 10'b0000000010;
    #1;
  i = 10'b0000000100;
    #1;
  i = 10'b0000001000;
    #1;
  i = 10'b0000010000;
    #1;
  i = 10'b0000100000;
    #1;
  i = 10'b0001000000;
    #1;
  i = 10'b0010000000;
    #1;
  i = 10'b0100000000;
    #1;
  i = 10'b1000000000;
    #1;
  i = 10'b0111111111;
    #1;
  i = 10'b1111111111;
  // Finalizar simulación
  #(DURATION) $display("Fin de la simulación");
  $finish;
end

endmodule

Guia3/eje3/a/ejercicio3a_tb.vcd
$date
	Fri May 30 09:51:14 2025
$end
$version
	Icarus Verilog
$end
$timescale
	1ps
$end
$scope module ejercicio3a_tb $end
$var wire 10 ! salida_tb [9:0] $end
$var parameter 32 " DURATION $end
$var reg 1 # clk $end
$var reg 10 $ i [9:0] $end
$var reg 1 % reset $end
$scope module UUT $end
$var wire 1 # clk $end
$var wire 10 & dec [9:0] $end
$var wire 1 % reset $end
$var reg 4 ' salida [3:0] $end
$upscope $end
$upscope $end
$enddefinitions $end
$comment Show the parameter values. $end
$dumpall
b1100100 "
$end
#0
$dumpvars
bx '
bx &
1%
bx $
0#
b0xxxx !
$end
#100000
b1111 !
b1111 '
b0 $
b0 &
0%
#200000
b0 !
b0 '
b1 $
b1 &
#300000
b1 !
b1 '
b10 $
b10 &
#400000
b10 !
b10 '
b100 $
b100 &
#500000
b11 !
b11 '
b1000 $
b1000 &
#600000
b100 !
b100 '
b10000 $
b10000 &
#700000
b101 !
b101 '
b100000 $
b100000 &
#800000
b110 !
b110 '
b1000000 $
b1000000 &
#900000
b111 !
b111 '
b10000000 $
b10000000 &
#1000000
b1000 !
b1000 '
b100000000 $
b100000000 &
#1100000
b1001 !
b1001 '
b1000000000 $
b1000000000 &
#1200000
b0xxxx !
bx '
b111111111 $
b111111111 &
#1300000
b1111111111 $
b1111111111 &
