Guia2/Ejercicio 3/eje3.v
module eje3 (
    input wire clk,
    input wire reset,
    input wire A,  // Cambiado a entrada
    input wire B,  // Cambiado a entrada
    input wire C,
    input wire D,
    output wire fa ,
    output wire fb ,
    output wire fc
);

    // Operación lógica para la salida
    assign fa = A | B | C | D;
    assign fb = A & B & C & D;
    assign fc = (D | C | ~A | ~B) & (D | ~C | B | ~A) & (~D | C | B | ~A) & (D | ~C | ~B | A) & (~D | C | ~B | A) & (~D | ~C | B | A);

endmodule

Guia2/Ejercicio 3/eje3_tb.v
`default_nettype none
`timescale 100 ns / 10 ns

module eje3_tb();

//-- Parámetro para definir cuánto dura la simulación
parameter DURATION = 100; // Cambiá esto según lo que necesites

//-- Señales de entrada del módulo
reg clk = 0;
reg reset;
reg d;  // Cambiado a reg para poder asignar valores
reg c;  // Cambiado a reg para poder asignar valores
reg b;  // Cambiado a reg para poder asignar valores
reg a;  // Cambiado a reg para poder asignar valores


//-- Instanciación del módulo bajo prueba
eje3 UUT (
    .clk(clk),
    .reset(reset),
    .A(a),
    .B(b),
    .C(c),  // Asignar un valor fijo a C
    .D(d)  // Asignar un valor fijo a D
);
integer n;

//-- Bloque inicial: estímulos y configuración
initial begin
  // Archivo para almacenar la traza
  $dumpfile("eje3_tb.vcd");
  $dumpvars(0, eje3_tb);
  reset = 1;
  #1;
  reset = 0;

  // Generar estímulos para las entradas
  // Cambiar los valores de a, b, c y d en cada ciclo

  for (n = 0; n < 16; n = n + 1) begin
    d = n[3]; // Cambiado a n[3] para asignar el bit correspondiente
    c = n[2]; // Cambiado a n[2] para asignar el bit correspondiente
    b = n[1]; // Cambiado a n[1] para asignar el bit correspondiente
    a = n[0]; // Cambiado a n[0] para asignar el bit correspondiente
    #1; // Esperar un ciclo de reloj
  end

  // Finalizar simulación
  #(DURATION) $display("Fin de la simulación");
  $finish;
end

endmodule

Guia2/Ejercicio 3/eje3_tb.vcd
$date
	Sat May 10 10:28:24 2025
$end
$version
	Icarus Verilog
$end
$timescale
	1ps
$end
$scope module eje3_tb $end
$var parameter 32 ! DURATION $end
$var reg 1 " a $end
$var reg 1 # b $end
$var reg 1 $ c $end
$var reg 1 % clk $end
$var reg 1 & d $end
$var reg 1 ' reset $end
$var integer 32 ( n [31:0] $end
$scope module UUT $end
$var wire 1 " A $end
$var wire 1 # B $end
$var wire 1 $ C $end
$var wire 1 & D $end
$var wire 1 % clk $end
$var wire 1 ) fa $end
$var wire 1 * fb $end
$var wire 1 + fc $end
$var wire 1 ' reset $end
$upscope $end
$upscope $end
$enddefinitions $end
$comment Show the parameter values. $end
$dumpall
b1100100 !
$end
#0
$dumpvars
x+
x*
x)
bx (
1'
x&
0%
x$
x#
x"
$end
#100000
1+
0)
0*
0"
0#
0$
0&
b0 (
0'
#200000
1)
1"
b1 (
#300000
1+
0"
1#
b10 (
#400000
0+
1"
b11 (
#500000
1+
0"
0#
1$
b100 (
#600000
0+
1"
b101 (
#700000
0"
1#
b110 (
#800000
1+
1"
b111 (
#900000
1+
0*
0"
0#
0$
1&
b1000 (
#1000000
0+
1"
b1001 (
#1100000
0"
1#
b1010 (
#1200000
1+
1"
b1011 (
#1300000
0+
0*
0"
0#
1$
b1100 (
#1400000
1+
1"
b1101 (
#1500000
0"
1#
b1110 (
#1600000
1*
1"
b1111 (
#1700000
b10000 (
