Guia2/Ejercicio 6/eje6.v
module eje6 (
    input wire clk,
    input wire reset,
    input wire A,  // Cambiado a entrada
    input wire B,  // Cambiado a entrada
    input wire C,
    input wire D,
    output wire f,    // Salida correcta
    output wire g,  // Salida correcta
    output wire h,   // Salida correcta
    output wire fPOS, // Salida correcta
    output wire fSOP, // Salida correcta
    output wire gPOS, // Salida correcta
    output wire gSOP, // Salida correcta
    output wire hPOS, // Salida correcta
    output wire hSOP  // Salida correcta
);

    // Operación lógica para la salida
    assign f = (A | ~B&C)&C;
    assign fPOS = (A | B | C)&(A | ~B | ~C)&(~A | B | C)&(~A | ~B | C)&(A | ~B | C);
    assign fSOP = (~A & ~B & C) | (A & ~B & C) | (A & B & C);

    assign g = A&~B&C | ~A&~B | A&B&~C&D;
    assign gPOS = (A | ~B | C | D)&(A | ~B | C | ~D)&(A | ~B | ~C | D)&(A | ~B | ~C | ~D)&(~A | B | C | D)&(~A | B | C | ~D)&(~A | ~B | C | D)&(~A | ~B | ~C | D)&(~A | ~B | ~C | ~D);
    assign gSOP = (~A & ~B & ~C & ~D)|(~A & ~B & ~C & D)|(~A & ~B & C & ~D)|(~A & ~B & C & D)|(A & ~B & C & ~D)|(A & ~B & C & D)|(A & B & ~C & D);

    assign h = A&B |C&D&(A&~B | C&D);
    assign hPOS = (A | B | C | D)&(A | B | C | ~D)&(A | B | ~C | D)&(A | ~B | C | D)&(A | ~B | C | ~D)&(A | ~B | ~C | D)&(~A | B | C | D)&(~A | B | C | ~D)&(~A | B | ~C | D);
    assign hSOP = (~A & ~B & C & D) | (~A & B & C & D)| (A & ~B & C & D)| (A & B & ~C & ~D)| (A & B & ~C & D)| (A & B & C & ~D)| (A & B & C & D);

endmodule

Guia2/Ejercicio 6/eje6_tb.v
`default_nettype none
`timescale 100 ns / 10 ns

module eje6_tb();

//-- Parámetro para definir cuánto dura la simulación
parameter DURATION = 100; // Cambiá esto según lo que necesites

//-- Señales de entrada del módulo
reg clk = 0;
reg reset;
reg A;  // Cambiado a reg para poder asignar valores
reg B;  // Cambiado a reg para poder asignar valores
reg C;
reg D;
wire f;  // Salida correcta
wire fPOS; // Salida correcta
wire fSOP; // Salida correcta

wire g;  // Salida correcta
wire gPOS; // Salida correcta
wire gSOP; // Salida correcta

wire h;  // Salida correcta
wire hPOS; // Salida correcta
wire hSOP; // Salida correcta


//-- Instanciación del módulo bajo prueba
eje6 UUT (
    .clk(clk),
    .reset(reset),
    .A(A),
    .B(B),
    .C(C),
    .D(D),
    .f(f),  // Salida correcta
    .fPOS(fPOS), // Salida correcta
    .fSOP(fSOP), // Salida correcta

    .g(g),  // Salida correcta
    .gPOS(gPOS), // Salida correcta
    .gSOP(gSOP), // Salida correcta

    .h(h),   // Salida correcta
    .hPOS(hPOS), // Salida correcta
    .hSOP(hSOP)  // Salida correcta
);
integer n;

//-- Bloque inicial: estímulos y configuración
initial begin
  // Archivo para almacenar la traza
  $dumpfile("eje6_tb.vcd");
  $dumpvars(0, eje6_tb);
  reset = 1;
  #1;
  reset = 0;
  /* para mostrar las tablas de verdad (ya vi que coinciden los resultados)
  $display("ABC | f | fPOS | fSOP");
  for (n = 0; n < 8; n = n + 1) begin
    {A,B,C}=n;
    #1; // Esperar un ciclo de reloj
    $fflush();
    $display("%b%b%b | %b | %b | %b",A, B, C, f,fPOS,fSOP);
  end

  $display("ABCD | g | gPOS | gSOP    h:| h | hPOS | hSOP");
  for (n = 0; n < 16; n = n + 1) begin
    {A,B,C,D}=n;
    #1; // Esperar un ciclo de reloj
    $fflush();
    $display("%b%b%b%b | %b | %b | %b    h:| %b | %b | %b",A, B, C, D, f,fPOS,fSOP,g,gPOS,gSOP);
  end
  */
  for (n = 0; n < 16; n = n + 1) begin
    {A,B,C,D}=n;
    #1; // Esperar un ciclo de reloj
  end


  // Finalizar simulación
  #(DURATION) $display("Fin de la simulación");
  $finish;
end

endmodule

Guia2/Ejercicio 6/eje6_tb.vcd
$date
	Sun May 11 11:31:48 2025
$end
$version
	Icarus Verilog
$end
$timescale
	1ps
$end
$scope module eje6_tb $end
$var wire 1 ! hSOP $end
$var wire 1 " hPOS $end
$var wire 1 # h $end
$var wire 1 $ gSOP $end
$var wire 1 % gPOS $end
$var wire 1 & g $end
$var wire 1 ' fSOP $end
$var wire 1 ( fPOS $end
$var wire 1 ) f $end
$var parameter 32 * DURATION $end
$var reg 1 + A $end
$var reg 1 , B $end
$var reg 1 - C $end
$var reg 1 . D $end
$var reg 1 / clk $end
$var reg 1 0 reset $end
$var integer 32 1 n [31:0] $end
$scope module UUT $end
$var wire 1 + A $end
$var wire 1 , B $end
$var wire 1 - C $end
$var wire 1 . D $end
$var wire 1 / clk $end
$var wire 1 ) f $end
$var wire 1 ( fPOS $end
$var wire 1 ' fSOP $end
$var wire 1 & g $end
$var wire 1 % gPOS $end
$var wire 1 $ gSOP $end
$var wire 1 # h $end
$var wire 1 " hPOS $end
$var wire 1 ! hSOP $end
$var wire 1 0 reset $end
$upscope $end
$upscope $end
$enddefinitions $end
$comment Show the parameter values. $end
$dumpall
b1100100 *
$end
#0
$dumpvars
bx 1
10
0/
x.
x-
x,
x+
x)
x(
x'
x&
x%
x$
x#
x"
x!
$end
#100000
1%
0"
1$
0!
0(
1&
0'
0#
0)
0+
0,
0-
0.
b0 1
00
#200000
1.
b1 1
#300000
1(
1)
1'
1-
0.
b10 1
#400000
1"
1!
1#
1.
b11 1
#500000
0%
0"
0!
0$
0(
0&
0'
0#
0)
1,
0-
0.
b100 1
#600000
1.
b101 1
#700000
0(
1-
0.
b110 1
#800000
1!
1"
1#
1.
b111 1
#900000
0!
0"
0#
1+
0,
0-
0.
b1000 1
#1000000
1.
b1001 1
#1100000
1%
1$
1(
1'
1&
1)
1-
0.
b1010 1
#1200000
1!
1#
1"
1.
b1011 1
#1300000
0%
1!
0(
0'
0&
0$
1"
0)
1,
0-
0.
b1100 1
#1400000
1%
1&
1$
1.
b1101 1
#1500000
0%
1(
1'
0&
0$
1)
1-
0.
b1110 1
#1600000
1.
b1111 1
#1700000
b10000 1
