Guia2/Ejercicio 4/eje4.v
module eje4 (
    input wire clk,
    input wire reset,
    input wire A,  // Cambiado a entrada
    input wire B,  // Cambiado a entrada
    input wire C,
    input wire D,
    input wire E,
    input wire F,
    output wire expresion1,   // Salida correcta
    output wire expresion2,   // Salida correcta
    output wire expresion3   // Salida correcta
);

    // Operación lógica para la salida
    assign expresion1 = ~((A & ~B) | (~C & D) | (E & F));
    assign expresion2 = ~(~(A | B&~C) | (D&~(E | ~F)));
    assign expresion3 = ~(~(A&B) & (C&D | ~E&F) & (~(A&B) | ~(C&D)));

endmodule

Guia2/Ejercicio 4/eje4_tb.v
`default_nettype none
`timescale 100 ns / 10 ns

module eje4_tb();

//-- Parámetro para definir cuánto dura la simulación
parameter DURATION = 1000; // Cambiá esto según lo que necesites

//-- Señales de entrada del módulo
reg clk ;
reg reset;
reg a;
reg b;
reg c;
reg d;
reg e;
reg f;
wire expresion1;
wire expresion2;
wire expresion3;
//-- Señales de salida del módulo
//-- Instanciación del módulo bajo prueba
eje4 UUT (
    .clk(clk),
    .reset(reset),
    .A(a),
    .B(b),
    .C(c),
    .D(d),
    .E(e),
    .F(f),
    .expresion1(expresion1),
    .expresion2(expresion2),
    .expresion3(expresion3)
);
integer n;

//-- Bloque inicial: estímulos y configuración
initial begin
  // Archivo para almacenar la traza
  clk= 0;
  $dumpfile("eje4_tb.vcd");
  $dumpvars(0, eje4_tb);
  reset = 1;
  #1;
  reset = 0;

  // Generar estímulos para las entradas
  $strobe("ABCDEF | expresion1 | expresion2 | expresion3 \n");
  for (n = 0; n < 64; n = n + 1) begin
    {a, b, c, d, e, f} = n; // Asignar valores a las entradas, transforma n en binario y asigna a las entradas
    #1; // Esperar un ciclo de reloj
    $fflush();
    $strobe("%b%b%b%b%b%b | %b ", a, b, c, d, e, f, expresion3);
    #1;
    //realizo el display despues de agregar un delay para que se lleguen a propagar los valores internos y utilizo strobe pq con display se llena el buffer
  end

  // Finalizar simulación
  #(DURATION) $strobe("Fin de la simulación");

  #2
  $finish;
end

endmodule

Guia2/Ejercicio 4/eje4_tb.vcd
$date
	Sat May 10 13:35:55 2025
$end
$version
	Icarus Verilog
$end
$timescale
	1ps
$end
$scope module eje4_tb $end
$var wire 1 ! expresion3 $end
$var wire 1 " expresion2 $end
$var wire 1 # expresion1 $end
$var parameter 32 $ DURATION $end
$var reg 1 % a $end
$var reg 1 & b $end
$var reg 1 ' c $end
$var reg 1 ( clk $end
$var reg 1 ) d $end
$var reg 1 * e $end
$var reg 1 + f $end
$var reg 1 , reset $end
$var integer 32 - n [31:0] $end
$scope module UUT $end
$var wire 1 % A $end
$var wire 1 & B $end
$var wire 1 ' C $end
$var wire 1 ) D $end
$var wire 1 * E $end
$var wire 1 + F $end
$var wire 1 ( clk $end
$var wire 1 # expresion1 $end
$var wire 1 " expresion2 $end
$var wire 1 ! expresion3 $end
$var wire 1 , reset $end
$upscope $end
$upscope $end
$enddefinitions $end
$comment Show the parameter values. $end
$dumpall
b1111101000 $
$end
#0
$dumpvars
bx -
1,
x+
x*
x)
0(
x'
x&
x%
x#
x"
x!
$end
#100000
1!
0"
1#
0%
0&
0'
0)
0*
0+
b0 -
0,
#300000
0!
1+
b1 -
#500000
1!
1*
0+
b10 -
#700000
0#
1+
b11 -
#900000
0#
1)
0*
0+
b100 -
#1100000
0!
1+
b101 -
#1300000
1!
1*
0+
b110 -
#1500000
1+
b111 -
#1700000
1#
1'
0)
0*
0+
b1000 -
#1900000
0!
1+
b1001 -
#2100000
1!
1*
0+
b1010 -
#2300000
0#
1+
b1011 -
#2500000
0!
1#
1)
0*
0+
b1100 -
#2700000
1+
b1101 -
#2900000
1*
0+
b1110 -
#3100000
0#
1+
b1111 -
#3300000
1"
1!
1#
1&
0'
0)
0*
0+
b10000 -
#3500000
0!
1+
b10001 -
#3700000
1!
1*
0+
b10010 -
#3900000
0#
1+
b10011 -
#4100000
0#
1)
0*
0+
b10100 -
#4300000
0"
0!
1+
b10101 -
#4500000
1"
1!
1*
0+
b10110 -
#4700000
1+
b10111 -
#4900000
0"
1#
1'
0)
0*
0+
b11000 -
#5100000
0!
1+
b11001 -
#5300000
1!
1*
0+
b11010 -
#5500000
0#
1+
b11011 -
#5700000
0!
1#
1)
0*
0+
b11100 -
#5900000
1+
b11101 -
#6100000
1*
0+
b11110 -
#6300000
0#
1+
b11111 -
#6500000
1!
1"
0#
1%
0&
0'
0)
0*
0+
b100000 -
#6700000
0!
1+
b100001 -
#6900000
1!
1*
0+
b100010 -
#7100000
1+
b100011 -
#7300000
1)
0*
0+
b100100 -
#7500000
0"
0!
1+
b100101 -
#7700000
1"
1!
1*
0+
b100110 -
#7900000
1+
b100111 -
#8100000
1'
0)
0*
0+
b101000 -
#8300000
0!
1+
b101001 -
#8500000
1!
1*
0+
b101010 -
#8700000
1+
b101011 -
#8900000
0!
1)
0*
0+
b101100 -
#9100000
0"
1+
b101101 -
#9300000
1"
1*
0+
b101110 -
#9500000
1+
b101111 -
#9700000
1#
1!
1&
0'
0)
0*
0+
b110000 -
#9900000
1+
b110001 -
#10100000
1*
0+
b110010 -
#10300000
0#
1+
b110011 -
#10500000
0#
1)
0*
0+
b110100 -
#10700000
0"
1+
b110101 -
#10900000
1"
1*
0+
b110110 -
#11100000
1+
b110111 -
#11300000
1#
1'
0)
0*
0+
b111000 -
#11500000
1+
b111001 -
#11700000
1*
0+
b111010 -
#11900000
0#
1+
b111011 -
#12100000
1#
1)
0*
0+
b111100 -
#12300000
0"
1+
b111101 -
#12500000
1"
1*
0+
b111110 -
#12700000
0#
1+
b111111 -
#12900000
b1000000 -
