Guia2/Ejercicio 4/eje4.v
module eje4 (
    input wire clk,
    input wire reset,
    input wire A,  // Cambiado a entrada
    input wire B,  // Cambiado a entrada
    input wire C,
    input wire D,
    input wire E,
    input wire F,
    output wire expresion1,   // Salida correcta
    output wire expresion2,   // Salida correcta
    output wire expresion3   // Salida correcta
);

    // Operación lógica para la salida
    assign expresion1 = ~((A & ~B) | (~C & D) | (E & F));
    assign expresion2 = ~(~(A | B & ~C) | D & ~(E | ~F));
    assign expresion3 = ~(~A&B & (C&D | ~E&F) & (~(A&B) | ~(C&D)));

endmodule

Guia2/Ejercicio 4/eje4_tb.v
`default_nettype none
`timescale 100 ns / 10 ns

module eje4_tb();

//-- Parámetro para definir cuánto dura la simulación
parameter DURATION = 100; // Cambiá esto según lo que necesites

//-- Señales de entrada del módulo
reg clk = 0;
reg reset;
reg a;
reg b;
reg c;
reg d;
reg e;
reg f;
wire expresion1;
wire expresion2;
wire expresion3;
//-- Señales de salida del módulo
//-- Instanciación del módulo bajo prueba
eje4 UUT (
    .clk(clk),
    .reset(reset),
    .A(a),
    .B(b),
    .C(c),
    .D(d),
    .E(e),
    .F(f),
    .expresion1(expresion1),
    .expresion2(expresion2),
    .expresion3(expresion3)
);
integer n;

//-- Bloque inicial: estímulos y configuración
initial begin
  // Archivo para almacenar la traza
  $dumpfile("eje4_tb.vcd");
  $dumpvars(0, eje4_tb);
  reset = 1;
  #1;
  reset = 0;

  // Generar estímulos para las entradas
  $display("ABCDEF | expresion1 | expresion2 | expresion3 \n");
  for (n = 0; n < 64; n = n + 1) begin
    {a, b, c, d, e, f} = n; // Asignar valores a las entradas, transforma n en binario y asigna a las entradas
    $display("%b%b%b%b%b%b | %b | %b | %b", a, b, c, d, e, f, expresion1, expresion2, expresion3);
    #1; // Esperar un ciclo de reloj
  end

  // Finalizar simulación
  #(DURATION) $display("Fin de la simulación");
  $finish;
end

endmodule

Guia2/Ejercicio 4/eje4_tb.vcd
$date
	Sat May 10 12:10:16 2025
$end
$version
	Icarus Verilog
$end
$timescale
	1ps
$end
$scope module eje4_tb $end
$var wire 1 ! expresion3 $end
$var wire 1 " expresion2 $end
$var wire 1 # expresion1 $end
$var parameter 32 $ DURATION $end
$var reg 1 % a $end
$var reg 1 & b $end
$var reg 1 ' c $end
$var reg 1 ( clk $end
$var reg 1 ) d $end
$var reg 1 * e $end
$var reg 1 + f $end
$var reg 1 , reset $end
$var integer 32 - n [31:0] $end
$scope module UUT $end
$var wire 1 % A $end
$var wire 1 & B $end
$var wire 1 ' C $end
$var wire 1 ) D $end
$var wire 1 * E $end
$var wire 1 + F $end
$var wire 1 ( clk $end
$var wire 1 # expresion1 $end
$var wire 1 " expresion2 $end
$var wire 1 ! expresion3 $end
$var wire 1 , reset $end
$upscope $end
$upscope $end
$enddefinitions $end
$comment Show the parameter values. $end
$dumpall
b1100100 $
$end
#0
$dumpvars
bx -
1,
x+
x*
x)
0(
x'
x&
x%
x#
x"
x!
$end
#100000
0"
1!
1#
0%
0&
0'
0)
0*
0+
b0 -
0,
#200000
1+
b1 -
#300000
1*
0+
b10 -
#400000
0#
1+
b11 -
#500000
0#
1)
0*
0+
b100 -
#600000
1+
b101 -
#700000
1*
0+
b110 -
#800000
1+
b111 -
#900000
1#
1'
0)
0*
0+
b1000 -
#1000000
1+
b1001 -
#1100000
1*
0+
b1010 -
#1200000
0#
1+
b1011 -
#1300000
1#
1)
0*
0+
b1100 -
#1400000
1+
b1101 -
#1500000
1*
0+
b1110 -
#1600000
0#
1+
b1111 -
#1700000
1"
1#
1&
0'
0)
0*
0+
b10000 -
#1800000
0!
1+
b10001 -
#1900000
1!
1*
0+
b10010 -
#2000000
0#
1+
b10011 -
#2100000
0#
1)
0*
0+
b10100 -
#2200000
0"
0!
1+
b10101 -
#2300000
1"
1!
1*
0+
b10110 -
#2400000
1+
b10111 -
#2500000
0"
1#
1'
0)
0*
0+
b11000 -
#2600000
0!
1+
b11001 -
#2700000
1!
1*
0+
b11010 -
#2800000
0#
1+
b11011 -
#2900000
0!
1#
1)
0*
0+
b11100 -
#3000000
1+
b11101 -
#3100000
1*
0+
b11110 -
#3200000
0#
1+
b11111 -
#3300000
1"
1!
0#
1%
0&
0'
0)
0*
0+
b100000 -
#3400000
1+
b100001 -
#3500000
1*
0+
b100010 -
#3600000
1+
b100011 -
#3700000
1)
0*
0+
b100100 -
#3800000
0"
1+
b100101 -
#3900000
1"
1*
0+
b100110 -
#4000000
1+
b100111 -
#4100000
1'
0)
0*
0+
b101000 -
#4200000
1+
b101001 -
#4300000
1*
0+
b101010 -
#4400000
1+
b101011 -
#4500000
1)
0*
0+
b101100 -
#4600000
0"
1+
b101101 -
#4700000
1"
1*
0+
b101110 -
#4800000
1+
b101111 -
#4900000
1#
1&
0'
0)
0*
0+
b110000 -
#5000000
1+
b110001 -
#5100000
1*
0+
b110010 -
#5200000
0#
1+
b110011 -
#5300000
0#
1)
0*
0+
b110100 -
#5400000
0"
1+
b110101 -
#5500000
1"
1*
0+
b110110 -
#5600000
1+
b110111 -
#5700000
1#
1'
0)
0*
0+
b111000 -
#5800000
1+
b111001 -
#5900000
1*
0+
b111010 -
#6000000
0#
1+
b111011 -
#6100000
1#
1)
0*
0+
b111100 -
#6200000
0"
1+
b111101 -
#6300000
1"
1*
0+
b111110 -
#6400000
0#
1+
b111111 -
#6500000
b1000000 -
