Guia2/Ejercicio 2/eje2.v
module eje2 (
    input wire clk,
    input wire reset,
    input wire A,  // Cambiado a entrada
    input wire B,  // Cambiado a entrada
    input wire C,  // Cambiado a entrada
    output wire nor1    // Salida correcta
);

    // Operación lógica para la salida
    assign nor1 = ~(A | B | C);

endmodule

Guia2/Ejercicio 2/eje2_tb.v
`default_nettype none
`timescale 100 ns / 10 ns

module eje2_tb();

//-- Parámetro para definir cuánto dura la simulación
parameter DURATION = 100; // Cambiá esto según lo que necesites

//-- Señales de entrada del módulo
reg clk = 0;
reg reset;
reg val1;  // Cambiado a reg para poder asignar valores
reg val2;  // Cambiado a reg para poder asignar valores
reg val3;  // Cambiado a reg para poder asignar valores

//-- Señales de salida del módulo
wire nor1;  // Salida del módulo bajo prueba

reg [18:0] j ;
reg [18:0] i ;
reg [18:0] z ;

//-- Instanciación del módulo bajo prueba
eje2 UUT (
    .clk(clk),
    .reset(reset),
    .A(val1),
    .B(val2),
    .C(val3),
    .nor1(nor1)
);
integer n;

//-- Bloque inicial: estímulos y configuración
initial begin
  // Archivo para almacenar la traza
  $dumpfile("eje2_tb.vcd");
  $dumpvars(0, eje2_tb);
  reset = 1;
  #1;
  reset = 0;

  // Generar estímulos para las entradas
  i = 19'b0111111000011110000;
  j = 19'b0000111100001111000;
  z = 19'b0010010001000100010;

  for (n = 0; n < 19 ; n = n + 1) begin
    val1 = i[18-n];
    val2 = j[18-n];
    val3 = z[18-n];
    #1; // Esperar un ciclo de reloj
  end

  // Finalizar simulación
  #(DURATION) $display("Fin de la simulación");
  $finish;
end

endmodule

Guia2/Ejercicio 2/eje2_tb.vcd
$date
	Sat May 10 09:36:28 2025
$end
$version
	Icarus Verilog
$end
$timescale
	1ps
$end
$scope module eje2_tb $end
$var wire 1 ! nor1 $end
$var parameter 32 " DURATION $end
$var reg 1 # clk $end
$var reg 19 $ i [18:0] $end
$var reg 19 % j [18:0] $end
$var reg 1 & reset $end
$var reg 1 ' val1 $end
$var reg 1 ( val2 $end
$var reg 1 ) val3 $end
$var reg 19 * z [18:0] $end
$var integer 32 + n [31:0] $end
$scope module UUT $end
$var wire 1 ' A $end
$var wire 1 ( B $end
$var wire 1 ) C $end
$var wire 1 # clk $end
$var wire 1 ! nor1 $end
$var wire 1 & reset $end
$upscope $end
$upscope $end
$enddefinitions $end
$comment Show the parameter values. $end
$dumpall
b1100100 "
$end
#0
$dumpvars
bx +
bx *
x)
x(
x'
1&
bx %
bx $
0#
x!
$end
#100000
1!
0)
0(
0'
b0 +
b10010001000100010 *
b111100001111000 %
b111111000011110000 $
0&
#200000
0!
1'
b1 +
#300000
1)
b10 +
#400000
0)
b11 +
#500000
1(
b100 +
#600000
1)
b101 +
#700000
0)
b110 +
#800000
0'
b111 +
#900000
1!
0(
b1000 +
#1000000
0!
1)
b1001 +
#1100000
1!
0)
b1010 +
#1200000
0!
1'
b1011 +
#1300000
1(
b1100 +
#1400000
1)
b1101 +
#1500000
0)
b1110 +
#1600000
0'
b1111 +
#1700000
1!
0(
b10000 +
#1800000
0!
1)
b10001 +
#1900000
1!
0)
b10010 +
#2000000
b10011 +
