Guia2/Ejericicio 5/eje5.v
module eje5 (
    input wire clk,
    input wire reset,
    input wire A,  // Cambiado a entrada
    input wire B,  // Cambiado a entrada
    input wire C,
    output wire A1,   // Salida correcta
    output wire A2,   // Salida correcta
    output wire B1,
    output wire B2,
    output wire C1,
    output wire C2,
    output wire D1,
    output wire D2
);

    // Operación lógica para la salida
    assign A1 = A&((~A) | (A&B));
    assign A2 = A&B;
    assign B1 = (A&B) | (~A&B);
    assign B2 = B;
    assign C1 = A&B | A&(B|C) | B&(B|C);
    assign C2 = B | A&C;
    assign D1 = (A | ~A)&(A&B | A&B&C);
    assign D2 = A&B;


endmodule

Guia2/Ejercicio 5/eje5_tb.v
`default_nettype none
`timescale 100 ns / 10 ns

module eje5_tb();

//-- Parámetro para definir cuánto dura la simulación
parameter DURATION = 1000; // Cambiá esto según lo que necesites

//-- Señales de entrada del módulo
reg clk ;
reg reset;
reg a;
reg b;
reg c;
//-- Señales de salida del módulo
//-- Instanciación del módulo bajo prueba
eje5 UUT (
    .clk(clk),
    .reset(reset),
    .A(a),
    .B(b),
    .C(c)
);
integer n;

//-- Bloque inicial: estímulos y configuración
initial begin
  // Archivo para almacenar la traza
  clk= 0;
  $dumpfile("eje5_tb.vcd");
  $dumpvars(0, eje5_tb);
  reset = 1;
  #1;
  reset = 0;

  // Generar estímulos para las entradas
  for (n = 0; n < 8; n = n + 1) begin
    if(n<4) begin
      {a, b} = n; // Asignar valores a las entradas, transforma n en binario y asigna a las entradas
    end
    if(n<8)begin
      {a, b, c} = n; // Asignar valores a las entradas, transforma n en binario y asigna a las entradas
    end
    #1;
  end
  a=0;
  b=0;
  c=0;
  // Finalizar simulación
  #(DURATION) $strobe("Fin de la simulación");

  #2
  $finish;
end

endmodule

Guia2/Ejercicio 5/eje5_tb.vcd
$date
	Sat May 10 16:24:29 2025
$end
$version
	Icarus Verilog
$end
$timescale
	1ps
$end
$scope module eje5_tb $end
$var parameter 32 ! DURATION $end
$var reg 1 " a $end
$var reg 1 # b $end
$var reg 1 $ c $end
$var reg 1 % clk $end
$var reg 1 & reset $end
$var integer 32 ' n [31:0] $end
$scope module UUT $end
$var wire 1 " A $end
$var wire 1 ( A1 $end
$var wire 1 ) A2 $end
$var wire 1 # B $end
$var wire 1 * B1 $end
$var wire 1 + B2 $end
$var wire 1 $ C $end
$var wire 1 , C1 $end
$var wire 1 - C2 $end
$var wire 1 . D1 $end
$var wire 1 / D2 $end
$var wire 1 % clk $end
$var wire 1 & reset $end
$upscope $end
$upscope $end
$enddefinitions $end
$comment Show the parameter values. $end
$dumpall
b1111101000 !
$end
#0
$dumpvars
x/
x.
x-
x,
x+
x*
x)
x(
bx '
1&
0%
x$
x#
x"
$end
#100000
0,
0.
0-
0*
0(
0)
0/
0$
0"
0+
0#
b0 '
0&
#200000
1$
0+
0#
b1 '
#300000
1*
1,
1-
1+
1#
0$
0"
b10 '
#400000
1$
0"
b11 '
#500000
0*
0,
0(
0-
1"
0+
0#
0$
b100 '
#600000
1,
1-
1$
b101 '
#700000
1(
1.
1*
1)
1/
1+
1#
0$
b110 '
#800000
1$
b111 '
#900000
0,
0*
0.
0-
0(
0)
0/
0$
0+
0#
0"
b1000 '
