TPF_2025/TPF_2025/leds_out.v
module leds_out(
    input wire [2:0]c,
    input wire s,
    output wire LED0,
    output wire LED1,
    output wire LED2,
    output wire LED3
);
assign LED0 = c[0];
assign LED1 = c[1];
assign LED2 = c[2];
assign LED3 = s;

endmodule

TPF_2025/TPF_2025/contador.v
module contador(
    input wire clk,
    input wire reset,
    input wire x,
    input wire y,
    output reg s,
    output reg [2:0] c
);

localparam [2:0]
    S0 = 3'b000,
    S1 = 3'b001,
    S2 = 3'b010,
    S3 = 3'b011,
    S4 = 3'b100,
    S5 = 3'b101,
    S6 = 3'b110,
    S7 = 3'b111;

reg [2:0] state, nextstate;

always@(posedge clk or posedge reset)
begin
    if(reset)
        state <= S0;
    else
        state <= nextstate;
end

always @(*) begin
    nextstate = state;
    s= 0; // Inicializar S en 0
    case(state)
        S0: case ({x, y})
                2'b00: begin nextstate = S0; s=0; end
                2'b10: begin nextstate = S1; s=0; end
                2'b01: begin nextstate = S0; s=0; end  // No puede suceder
                2'b11: begin nextstate = S0; s=0; end  // No puede suceder
            endcase
        S1: case ({x, y})
                2'b00: begin nextstate = S1; s=0; end
                2'b10: begin nextstate = S2; s=0; end
                2'b01: begin nextstate = S0; s=0; end
                2'b11: begin nextstate = S1; s=0; end  // No puede suceder
            endcase
        S2: case ({x, y})
                2'b00: begin nextstate = S2; s=0; end
                2'b10: begin nextstate = S3; s=0; end
                2'b01: begin nextstate = S1; s=0; end
                2'b11: begin nextstate = S2; s=0; end  // No puede suceder
            endcase
        S3: case ({x, y})
                2'b00: begin nextstate = S3; s=0; end
                2'b10: begin nextstate = S4; s=0; end
                2'b01: begin nextstate = S2; s=0; end
                2'b11: begin nextstate = S3; s=0; end  // No puede suceder
            endcase
        S4: case ({x, y})
                2'b00: begin nextstate = S4; s=0; end
                2'b10: begin nextstate = S5; s=0; end
                2'b01: begin nextstate = S3; s=0; end
                2'b11: begin nextstate = S4; s=0; end  // No puede suceder
            endcase
        S5: case ({x, y})
                2'b00: begin nextstate = S5; s=0; end
                2'b10: begin nextstate = S6; s=0; end
                2'b01: begin nextstate = S4; s=0; end
                2'b11: begin nextstate = S5; s=0; end  // No puede suceder
            endcase
        S6: case ({x, y})
                2'b00: begin nextstate = S6; s=0; end
                2'b10: begin nextstate = S7; s=1; end
                2'b01: begin nextstate = S5; s=0; end
                2'b11: begin nextstate = S6; s=0; end  // No puede suceder
            endcase
        S7: case ({x, y})
                2'b00: begin nextstate = S7; s=1; end
                2'b10: begin nextstate = S7; s=0; end  // No puede suceder
                2'b01: begin nextstate = S6; s=0; end
                2'b11: begin nextstate = S7; s=0; end  // No puede suceder
        default: begin nextstate = S0; s=0; end
        endcase
endcase
end
always@* begin
    case(state)
        S0: c = 3'b000;
        S1: c = 3'b001;
        S2: c = 3'b010;
        S3: c = 3'b011;
        S4: c = 3'b100;
        S5: c = 3'b101;
        S6: c = 3'b110;
        S7: c = 3'b111;
        default: c = 3'b000;
    endcase
end



endmodule

TPF_2025/TPF_2025/sensores.v
module sensores (
    input wire clk,
    input wire reset,
    input wire a,
    input wire b,
    output reg x0,
    output reg y0
);

localparam [2:0]
    S0 = 3'b000,
    S1 = 3'b001,
    S2 = 3'b010,
    S3 = 3'b011,
    S4 = 3'b100,
    S5 = 3'b101,
    S6 = 3'b110;

reg [2:0] state, nextstate;

/*always@(posedge clk, posedge reset)
begin
    if(reset)
      begin
        state<=S0;
      end
    else
       begin
        state<=nextstate;
       end
end*/
reg x,y;
always @* begin
    nextstate = state;
    x = 0;
    y = 0;
    case(state)
        S0: case ({a, b})
                2'b00: begin nextstate = S0; x = 0; y = 0; end
                2'b10: begin nextstate = S1; x = 0; y = 0; end
                2'b01: begin nextstate = S2; x = 0; y = 0; end
                2'b11: begin nextstate = S0; x = 0; y = 0; end
            endcase
        S1: case ({a, b})
                2'b00: begin nextstate = S0; x = 0; y = 0; end
                2'b10: begin nextstate = S1; x = 0; y = 0; end
                2'b01: begin nextstate = S0; x = 0; y = 0; end
                2'b11: begin nextstate = S3; x = 0; y = 0; end // ejemplo: x=1 en esta transición
            endcase
        S2: case ({a, b})
                2'b00: begin nextstate = S0; x = 0; y = 0; end
                2'b10: begin nextstate = S1; x = 0; y = 0; end
                2'b01: begin nextstate = S2; x = 0; y = 0; end
                2'b11: begin nextstate = S4; x = 0; y = 0; end // ejemplo: y=1 en esta transición
            endcase
        S3: case ({a, b})
                2'b00: begin nextstate = S0; x = 0; y = 0; end
                2'b10: begin nextstate = S2; x = 0; y = 0; end
                2'b01: begin nextstate = S5; x = 0; y = 0; end
                2'b11: begin nextstate = S3; x = 0; y = 0; end
            endcase
        S4: case ({a, b})
                2'b00: begin nextstate = S0; x = 0; y = 0; end
                2'b10: begin nextstate = S1; x = 0; y = 0; end
                2'b01: begin nextstate = S6; x = 0; y = 0; end
                2'b11: begin nextstate = S4; x = 0; y = 0; end
            endcase
        S5: case ({a, b})
                2'b00: begin nextstate = S0; x = 1; y = 0; end
                2'b10: begin nextstate = S2; x = 0; y = 0; end
                2'b01: begin nextstate = S5; x = 0; y = 0; end
                2'b11: begin nextstate = S3; x = 0; y = 0; end
            endcase
        S6: case ({a, b})
                2'b00: begin nextstate = S0; x = 0; y = 1; end
                2'b10: begin nextstate = S1; x = 0; y = 0; end
                2'b01: begin nextstate = S6; x = 0; y = 0; end
                2'b11: begin nextstate = S4; x = 0; y = 0; end
            endcase
        default: begin nextstate = S0; x = 0; y = 0; end
    endcase
end
always @(posedge clk or posedge reset) begin
    if (reset) begin
        state <= S0;
        x0 <= 0;
        y0 <= 0;
    end else begin
        state <= nextstate;
        x0 <= x;
        y0 <= y;
    end
end
endmodule

TPF_2025/TPF_2025/mostrarFPGA.v
module mostrarFPGA(
    input wire clk,
    input wire BTN1,  // Sensor a
    input wire BTN2,  // Sensor b
    output wire [3:0] leds, // Salida a los LEDS (3 bits)
    input wire reset
);

    wire x;
    wire y;

    wire [2:0] c;
    // FSM que detecta si entra o sale un auto
    sensores fsm(
        .clk(clk),
        .reset(reset),
        .a(BTN1),
        .b(BTN2),
        .x0(x),
        .y0(y)
    );
    wire s;
    // Contador ascendente/descendente
    contador cuenta (
        .clk(clk),
        .reset(reset),
        .x(x),
        .y(y),
        .s(s),
        .c(c)
    );

    // Módulo para mostrar en LEDS
    wire l0;
    wire l1;
    wire l2;
    wire l3;
    leds_out mostar_leds_out (
        .c(c),
        .s(s),
        .LED0(l0),
        .LED1(l1),
        .LED2(l2),
        .LED3(l3)
    );
    assign leds = {l3,l2,l1,l0};

endmodule

TPF_2025/TPF_2025/mostrarFPGA_tb.v
`default_nettype none
`define DUMPSTR(x) `"x.vcd`"
`timescale 100 ns / 10 ns

module mostrarFPGA_tb;
    parameter DURATION = 10;

    reg clk = 0;
    reg BTN1 = 0;
    reg BTN2 = 0;
    wire [3:0] leds;

    // Instanciamos el módulo top
    mostrarFPGA uut (
        .clk(clk),
        .BTN1(BTN1),
        .BTN2(BTN2),
        .leds(leds)
    );

    // Reloj de 10ns (100 MHz)
    always #5 clk = ~clk;

    // Simulación de pulsos de botón con rebote
    initial begin
        $dumpfile(`DUMPSTR(`VCD_OUTPUT));
        $dumpvars(0, mostrarFPGA_tb);
        BTN1 = 1;
        BTN2 = 0;

        #50
        BTN1 = 1;
        BTN2 = 1;

        #50
        BTN1 = 0;
        BTN2 = 1;

        #50
        BTN1 = 0;
        BTN2 = 0;

        #50
        #(DURATION) $display("End of simulation");
        $finish;
    end

endmodule

TPF_2025/TPF_2025/mostrarFPGA_tb.vcd
$date
	Thu Jun 19 17:43:32 2025
$end
$version
	Icarus Verilog
$end
$timescale
	1ps
$end
$scope module mostrarFPGA_tb $end
$var wire 4 ! leds [3:0] $end
$var parameter 32 " DURATION $end
$var reg 1 # BTN1 $end
$var reg 1 $ BTN2 $end
$var reg 1 % clk $end
$scope module uut $end
$var wire 1 # BTN1 $end
$var wire 1 $ BTN2 $end
$var wire 1 % clk $end
$var wire 1 & reset $end
$var wire 1 ' y $end
$var wire 1 ( x $end
$var wire 1 ) s $end
$var wire 4 * leds [3:0] $end
$var wire 1 + l3 $end
$var wire 1 , l2 $end
$var wire 1 - l1 $end
$var wire 1 . l0 $end
$var wire 3 / c [2:0] $end
$scope module cuenta $end
$var wire 1 % clk $end
$var wire 1 & reset $end
$var wire 1 ' y $end
$var wire 1 ( x $end
$var parameter 3 0 S0 $end
$var parameter 3 1 S1 $end
$var parameter 3 2 S2 $end
$var parameter 3 3 S3 $end
$var parameter 3 4 S4 $end
$var parameter 3 5 S5 $end
$var parameter 3 6 S6 $end
$var parameter 3 7 S7 $end
$var reg 3 8 c [2:0] $end
$var reg 3 9 nextstate [2:0] $end
$var reg 1 ) s $end
$var reg 3 : state [2:0] $end
$upscope $end
$scope module fsm $end
$var wire 1 # a $end
$var wire 1 $ b $end
$var wire 1 % clk $end
$var wire 1 & reset $end
$var parameter 3 ; S0 $end
$var parameter 3 < S1 $end
$var parameter 3 = S2 $end
$var parameter 3 > S3 $end
$var parameter 3 ? S4 $end
$var parameter 3 @ S5 $end
$var parameter 3 A S6 $end
$var reg 3 B nextstate [2:0] $end
$var reg 3 C state [2:0] $end
$var reg 1 D x $end
$var reg 1 ( x0 $end
$var reg 1 E y $end
$var reg 1 ' y0 $end
$upscope $end
$scope module mostar_leds_out $end
$var wire 1 + LED3 $end
$var wire 3 F c [2:0] $end
$var wire 1 ) s $end
$var wire 1 , LED2 $end
$var wire 1 - LED1 $end
$var wire 1 . LED0 $end
$upscope $end
$upscope $end
$upscope $end
$enddefinitions $end
$comment Show the parameter values. $end
$dumpall
b110 A
b101 @
b100 ?
b11 >
b10 =
b1 <
b0 ;
b111 7
b110 6
b101 5
b100 4
b11 3
b10 2
b1 1
b0 0
b1010 "
$end
#0
$dumpvars
bx F
0E
0D
bx C
b0 B
bx :
bx 9
bx 8
bx /
x.
x-
x,
x+
bx *
x)
x(
x'
z&
0%
0$
1#
bx !
$end
#500000
b0xxx !
b0xxx *
0+
0)
b1 B
0'
0(
b0 C
1%
#1000000
0%
#1500000
b1 C
1%
#2000000
0%
#2500000
1%
#3000000
0%
#3500000
1%
#4000000
0%
#4500000
1%
#5000000
b11 B
0%
1$
#5500000
b11 C
1%
#6000000
0%
#6500000
1%
#7000000
0%
#7500000
1%
#8000000
0%
#8500000
1%
#9000000
0%
#9500000
1%
#10000000
b101 B
0%
0#
#10500000
b101 C
1%
#11000000
0%
#11500000
1%
#12000000
0%
#12500000
1%
#13000000
0%
#13500000
1%
#14000000
0%
#14500000
1%
#15000000
1D
b0 B
0%
0$
#15500000
0D
1(
b0 C
1%
#16000000
0%
#16500000
0(
1%
