Guia2/Ejercicio 10/eje10.v
module eje10 (
    input wire clk,
    input wire reset,
    input wire A,  // Cambiado a entrada
    input wire B,  // Cambiado a entrada
    input wire C,
    input wire D,
    input wire E,
    output wire P,
    output wire T,
    output wire Df


);
    assign Dpar= ~E;
    assign T = ~A&~B&~C&~D&~E | ~A&B&C&~D&~E | A&B&~C&~D&~E | ~A&~B&~C&D&E  |  ~A&B&C&D&E| A&B&~C&D& E| A&B&C&D&~E | ~A&~B&C&D&~E  | A&~B&~C&D&~E | A&~B&C&~D&E     | ~A&B&~C&~D&E;
    /*ssign Df = A&B&~C&E | A&B&C&E | A&~B&~C&E | ~A&~B&~C&D | A&~B&D&E | ~A&C&~D&E | ~A&B&~C&D&E;*/
    assign P = ~A&B&~C&D&E | ~A&C&~D&E  | ~A&~B&C&E | ~A&~B&~C&D | A&B&C&E | A&~B&D&E | A&~B&~C&E;

    // Operación lógica para la salida




endmodule

Guia2/Ejercicio 10/es_div3.v
module es_div3 (
  input  [4:0] n,    // Entrada de 5 bits: puede representar 0 a 31
  output reg div3  // Salida: 1 si es primo, 0 si no
);
  always @(*) begin
    // Por defecto no es primo
    if (n % 3 ==0)
        div3 = 1;
    else
        div3 = 0;
  end
endmodule

Guia2/Ejercicio 10/es_par.v
module es_par (
  input  [4:0] n,    // Entrada de 5 bits: puede representar 0 a 31
  output reg par  // Salida: 1 si es primo, 0 si no
);
  always @(*) begin
    // Por defecto no es primo
    if (n % 2 ==0)
        par = 1;
    else
        par = 0;
  end
endmodule

Guia2/Ejercicio 10/es_primo.v
module es_primo (
  input  [4:0] n,    // Entrada de 5 bits: puede representar 0 a 31
  output reg primo  // Salida: 1 si es primo, 0 si no
);
  integer i;
  always @(*) begin
    // Por defecto no es primo
    if (n < 2)
      primo = 0;
    else begin
      primo = 1; // Asumimos que es primo
      for (i = 2; i <= n / 2; i = i + 1) begin
        if (n % i == 0) begin
          primo = 0; // Tiene un divisor: no es primo
        end
      end
    end
  end
endmodule

Guia2/Ejercicio 10/eje10_tb.v
`default_nettype none
`timescale 100 ns / 10 ns
module eje10_tb();

//-- Parámetro para definir cuánto dura la simulación
parameter DURATION = 100; // Cambiá esto según lo que necesites

//-- Señales de entrada del módulo
reg clk = 0;
reg reset;
reg A, B, C, D, E;
reg [4:0] n_tb;
wire is_prime;
wire is_par;
wire is_div3;
integer n;

//-- Instanciar el módulo es_primo
es_primo prime_checker (
  .n(n_tb),
  .primo(is_prime)
);
es_par par_checker (
  .n(n_tb),
  .par(is_par)
);
es_div3 div3_checker (
  .n(n_tb),
  .div3(is_div3)
);

eje10 UUT (
  .clk(clk),
  .reset(reset),
  .A(A),
  .B(B),
  .C(C),
  .D(D),
  .E(E)
);


//-- Bloque inicial: estímulos y configuración
initial begin
  // Archivo para almacenar la traza
  $dumpfile("eje10_tb.vcd");
  $dumpvars(0, eje10_tb);
  reset = 1;
  #1;
  reset = 0;
  for (n = 0; n < 32; n = n + 1) begin
    {A,B,C,D,E}=n;
    n_tb = n;
    #1; // Esperar un ciclo de reloj
    $fflush();
    $display("%d | %b%b%b%b%b | %b | %b | %b", n, A, B, C, D, E, is_prime,is_par,is_div3);
  end
  n_tb=32;
  A =0;
  B =0;
  C=0;
  D=0;
  E=0;


  // Finalizar simulación
  #(DURATION) $display("Fin de la simulación");
  $finish;
end

endmodule

Guia2/Ejercicio 10/eje10_tb.vcd
$date
	Sun May 11 19:54:58 2025
$end
$version
	Icarus Verilog
$end
$timescale
	1ps
$end
$scope module eje10_tb $end
$var wire 1 ! is_prime $end
$var wire 1 " is_par $end
$var wire 1 # is_div3 $end
$var parameter 32 $ DURATION $end
$var reg 1 % A $end
$var reg 1 & B $end
$var reg 1 ' C $end
$var reg 1 ( D $end
$var reg 1 ) E $end
$var reg 1 * clk $end
$var reg 5 + n_tb [4:0] $end
$var reg 1 , reset $end
$var integer 32 - n [31:0] $end
$scope module UUT $end
$var wire 1 % A $end
$var wire 1 & B $end
$var wire 1 ' C $end
$var wire 1 ( D $end
$var wire 1 . Df $end
$var wire 1 / Dpar $end
$var wire 1 ) E $end
$var wire 1 0 P $end
$var wire 1 1 T $end
$var wire 1 * clk $end
$var wire 1 , reset $end
$upscope $end
$scope module div3_checker $end
$var wire 5 2 n [4:0] $end
$var reg 1 # div3 $end
$upscope $end
$scope module par_checker $end
$var wire 5 3 n [4:0] $end
$var reg 1 " par $end
$upscope $end
$scope module prime_checker $end
$var wire 5 4 n [4:0] $end
$var reg 1 ! primo $end
$var integer 32 5 i [31:0] $end
$upscope $end
$upscope $end
$enddefinitions $end
$comment Show the parameter values. $end
$dumpall
b1100100 $
$end
#0
$dumpvars
bx 5
bx 4
bx 3
bx 2
x1
x0
x/
z.
bx -
1,
bx +
0*
x)
x(
x'
x&
x%
x#
x"
x!
$end
#100000
11
00
1#
1"
0!
1/
b0 +
b0 2
b0 3
b0 4
0%
0&
0'
0(
0)
b0 -
0,
#200000
01
0"
0#
0/
b1 +
b1 2
b1 3
b1 4
1)
b1 -
#300000
01
10
1"
b10 5
1!
1/
b10 +
b10 2
b10 3
b10 4
1(
0)
b10 -
#400000
11
0"
1#
0/
b11 +
b11 2
b11 3
b11 4
1)
b11 -
#500000
01
00
0#
1"
b11 5
0!
1/
b100 +
b100 2
b100 3
b100 4
1'
0(
0)
b100 -
#600000
10
b11 5
1!
0"
0/
b101 +
b101 2
b101 3
b101 4
1)
b101 -
#700000
00
11
1#
1"
0!
b100 5
1/
b110 +
b110 2
b110 3
b110 4
1(
0)
b110 -
#800000
01
10
b100 5
1!
0"
0#
0/
b111 +
b111 2
b111 3
b111 4
1)
b111 -
#900000
01
00
1"
0!
b101 5
1/
b1000 +
b1000 2
b1000 3
b1000 4
1&
0'
0(
0)
b1000 -
#1000000
11
b101 5
0!
0"
1#
0/
b1001 +
b1001 2
b1001 3
b1001 4
1)
b1001 -
#1100000
01
0#
1"
b110 5
0!
1/
b1010 +
b1010 2
b1010 3
b1010 4
1(
0)
b1010 -
#1200000
10
b110 5
1!
0"
0/
b1011 +
b1011 2
b1011 3
b1011 4
1)
b1011 -
#1300000
11
00
1#
1"
0!
b111 5
1/
b1100 +
b1100 2
b1100 3
b1100 4
1'
0(
0)
b1100 -
#1400000
01
10
b111 5
1!
0"
0#
0/
b1101 +
b1101 2
b1101 3
b1101 4
1)
b1101 -
#1500000
01
00
1"
0!
b1000 5
1/
b1110 +
b1110 2
b1110 3
b1110 4
1(
0)
b1110 -
#1600000
11
b1000 5
0!
0"
1#
0/
b1111 +
b1111 2
b1111 3
b1111 4
1)
b1111 -
#1700000
01
0#
1"
b1001 5
0!
1/
b10000 +
b10000 2
b10000 3
b10000 4
1%
0&
0'
0(
0)
b10000 -
#1800000
10
b1001 5
1!
0"
0/
b10001 +
b10001 2
b10001 3
b10001 4
1)
b10001 -
#1900000
11
00
1#
1"
0!
b1010 5
1/
b10010 +
b10010 2
b10010 3
b10010 4
1(
0)
b10010 -
#2000000
01
10
b1010 5
1!
0"
0#
0/
b10011 +
b10011 2
b10011 3
b10011 4
1)
b10011 -
#2100000
00
1"
0!
b1011 5
1/
b10100 +
b10100 2
b10100 3
b10100 4
1'
0(
0)
b10100 -
#2200000
11
b1011 5
0!
0"
1#
0/
b10101 +
b10101 2
b10101 3
b10101 4
1)
b10101 -
#2300000
01
0#
1"
b1100 5
0!
1/
b10110 +
b10110 2
b10110 3
b10110 4
1(
0)
b10110 -
#2400000
10
b1100 5
1!
0"
0/
b10111 +
b10111 2
b10111 3
b10111 4
1)
b10111 -
#2500000
11
00
1#
1"
0!
b1101 5
1/
b11000 +
b11000 2
b11000 3
b11000 4
1&
0'
0(
0)
b11000 -
#2600000
01
b1101 5
0!
0"
0#
0/
b11001 +
b11001 2
b11001 3
b11001 4
1)
b11001 -
#2700000
01
1"
b1110 5
0!
1/
b11010 +
b11010 2
b11010 3
b11010 4
1(
0)
b11010 -
#2800000
11
b1110 5
0!
0"
1#
0/
b11011 +
b11011 2
b11011 3
b11011 4
1)
b11011 -
#2900000
01
0#
1"
b1111 5
0!
1/
b11100 +
b11100 2
b11100 3
b11100 4
1'
0(
0)
b11100 -
#3000000
10
b1111 5
1!
0"
0/
b11101 +
b11101 2
b11101 3
b11101 4
1)
b11101 -
#3100000
11
00
1#
1"
0!
b10000 5
1/
b11110 +
b11110 2
b11110 3
b11110 4
1(
0)
b11110 -
#3200000
01
10
b10000 5
1!
0"
0#
0/
b11111 +
b11111 2
b11111 3
b11111 4
1)
b11111 -
#3300000
11
00
1/
1#
1"
0!
0)
0(
0'
0&
0%
b0 +
b0 2
b0 3
b0 4
b100000 -
