Guia2/Ejercicio 10/eje10.v
module eje10 (
    input wire clk,
    input wire reset,
    input wire A,  // Cambiado a entrada
    input wire B,  // Cambiado a entrada
    input wire C,
    input wire D,
    input wire E,
    output wire a1,
    output wire a2,
    output wire b1,
    output wire b2,
    output wire c1,
    output wire c2,
    output wire d1,
    output wire d2


);
    assign a1 = A&~B&C | ~A&B&~C | A&B&C;
    assign a2 = ~A&B&~C | A&C;
    assign b1 = (A | ~B)&(A | ~B | ~C)&(B | C | ~D)&(~A | B | ~C | D);
    assign b2 = ~B&~C&~D | A&C&D | ~A&~B&C | A&B;
    assign c1 = (A | B | C)&(~A | ~B | ~C)&(A | ~B | C);
    assign c2 =  A&~C | ~A&C | A&~B&C;
    assign d1 = ~A&B&~C&D&~E | ~A&~B&~C&D&E | A&~B&~C&D&E | A&B&~C&~D&~E | ~A&B&C&D&~E | ~A&B&C&~D&E | ~A&~B&~C&~D&~E | ~A&~B&C&D&E | A&B&~C&D&~E | A&B&~C&D&E;
    assign d2 = ~A&~B&~C&~D&~E | ~A&B&C&~D&E | A&B&~C&~E | A&B&~C&D | ~A&B&D&~E | ~B&~C&D&E | ~A&~B&D&E;
    // Operación lógica para la salida




endmodule

Guia2/Ejercicio 10/es_primo.v
module es_primo (
  input  [4:0] n,    // Entrada de 5 bits: puede representar 0 a 31
  output reg primo  // Salida: 1 si es primo, 0 si no
);
  integer i;
  always @(*) begin
    // Por defecto no es primo
    if (n < 2)
      primo = 0;
    else begin
      primo = 1; // Asumimos que es primo
      for (i = 2; i <= n / 2; i = i + 1) begin
        if (n % i == 0) begin
          primo = 0; // Tiene un divisor: no es primo
        end
      end
    end
  end
endmodule

Guia2/Ejercicio 10/eje10_tb.v
`default_nettype none
`timescale 100 ns / 10 ns
module eje10_tb();

//-- Parámetro para definir cuánto dura la simulación
parameter DURATION = 100; // Cambiá esto según lo que necesites

//-- Señales de entrada del módulo
reg clk = 0;
reg reset;
reg A, B, C, D, E;
reg [4:0] n_tb;
wire is_prime;
integer n;

//-- Instanciar el módulo es_primo
es_primo prime_checker (
  .n(n_tb),
  .primo(is_prime)
);
eje10 UUT (
  .clk(clk),
  .reset(reset),
  .A(A),
  .B(B),
  .C(C),
  .D(D),
  .E(E)
);


//-- Bloque inicial: estímulos y configuración
initial begin
  // Archivo para almacenar la traza
  $dumpfile("eje10_tb.vcd");
  $dumpvars(0, eje10_tb);
  reset = 1;
  #1;
  reset = 0;
  for (n = 0; n < 32; n = n + 1) begin
    {A,B,C,D,E}=n;
    n_tb = n;
    #1; // Esperar un ciclo de reloj
    $fflush();
    $display("%d | %b%b%b%b%b | %b", n, A, B, C, D, E, is_prime);
  end


  // Finalizar simulación
  #(DURATION) $display("Fin de la simulación");
  $finish;
end

endmodule

Guia2/Ejercicio 10/eje10_tb.vcd
$date
	Sun May 11 17:56:18 2025
$end
$version
	Icarus Verilog
$end
$timescale
	1ps
$end
$scope module eje10_tb $end
$var wire 1 ! is_prime $end
$var parameter 32 " DURATION $end
$var reg 1 # A $end
$var reg 1 $ B $end
$var reg 1 % C $end
$var reg 1 & D $end
$var reg 1 ' E $end
$var reg 1 ( clk $end
$var reg 5 ) n_tb [4:0] $end
$var reg 1 * reset $end
$var integer 32 + n [31:0] $end
$scope module UUT $end
$var wire 1 # A $end
$var wire 1 $ B $end
$var wire 1 % C $end
$var wire 1 & D $end
$var wire 1 ' E $end
$var wire 1 , a1 $end
$var wire 1 - a2 $end
$var wire 1 . b1 $end
$var wire 1 / b2 $end
$var wire 1 0 c1 $end
$var wire 1 1 c2 $end
$var wire 1 ( clk $end
$var wire 1 2 d1 $end
$var wire 1 3 d2 $end
$var wire 1 * reset $end
$upscope $end
$scope module prime_checker $end
$var wire 5 4 n [4:0] $end
$var reg 1 ! primo $end
$var integer 32 5 i [31:0] $end
$upscope $end
$upscope $end
$enddefinitions $end
$comment Show the parameter values. $end
$dumpall
b1100100 "
$end
#0
$dumpvars
bx 5
bx 4
x3
x2
x1
x0
x/
x.
x-
x,
bx +
1*
bx )
0(
x'
x&
x%
x$
x#
x!
$end
#100000
13
12
1/
1.
00
0,
0-
01
0!
b0 )
b0 4
0#
0$
0%
0&
0'
b0 +
0*
#200000
03
02
b1 )
b1 4
1'
b1 +
#300000
03
02
0/
0.
b10 5
1!
b10 )
b10 4
1&
0'
b10 +
#400000
12
13
b11 )
b11 4
1'
b11 +
#500000
02
1.
1/
10
11
03
b11 5
0!
b100 )
b100 4
1%
0&
0'
b100 +
#600000
b11 5
1!
b101 )
b101 4
1'
b101 +
#700000
0!
b100 5
b110 )
b110 4
1&
0'
b110 +
#800000
12
13
b100 5
1!
b111 )
b111 4
1'
b111 +
#900000
0.
1,
02
1-
0/
00
01
03
0!
b101 5
b1000 )
b1000 4
1$
0%
0&
0'
b1000 +
#1000000
b101 5
0!
b1001 )
b1001 4
1'
b1001 +
#1100000
12
13
b110 5
0!
b1010 )
b1010 4
1&
0'
b1010 +
#1200000
02
03
b110 5
1!
b1011 )
b1011 4
1'
b1011 +
#1300000
0,
0-
11
10
0!
b111 5
b1100 )
b1100 4
1%
0&
0'
b1100 +
#1400000
13
12
b111 5
1!
b1101 )
b1101 4
1'
b1101 +
#1500000
12
0!
b1000 5
b1110 )
b1110 4
1&
0'
b1110 +
#1600000
02
03
b1000 5
0!
b1111 )
b1111 4
1'
b1111 +
#1700000
1/
1.
10
b1001 5
0!
b10000 )
b10000 4
1#
0$
0%
0&
0'
b10000 +
#1800000
b1001 5
1!
b10001 )
b10001 4
1'
b10001 +
#1900000
0/
0.
0!
b1010 5
b10010 )
b10010 4
1&
0'
b10010 +
#2000000
12
13
b1010 5
1!
b10011 )
b10011 4
1'
b10011 +
#2100000
02
0/
1,
03
1-
0!
b1011 5
b10100 )
b10100 4
1%
0&
0'
b10100 +
#2200000
b1011 5
0!
b10101 )
b10101 4
1'
b10101 +
#2300000
1/
1.
b1100 5
0!
b10110 )
b10110 4
1&
0'
b10110 +
#2400000
b1100 5
1!
b10111 )
b10111 4
1'
b10111 +
#2500000
12
13
0,
0-
11
1.
0!
b1101 5
b11000 )
b11000 4
1$
0%
0&
0'
b11000 +
#2600000
02
03
b1101 5
0!
b11001 )
b11001 4
1'
b11001 +
#2700000
13
12
b1110 5
0!
b11010 )
b11010 4
1&
0'
b11010 +
#2800000
b1110 5
0!
b11011 )
b11011 4
1'
b11011 +
#2900000
03
00
01
1,
1-
02
b1111 5
0!
b11100 )
b11100 4
1%
0&
0'
b11100 +
#3000000
b1111 5
1!
b11101 )
b11101 4
1'
b11101 +
#3100000
0!
b10000 5
b11110 )
b11110 4
1&
0'
b11110 +
#3200000
b10000 5
1!
b11111 )
b11111 4
1'
b11111 +
#3300000
b100000 +
