Guia2/Ejercicio 7/eje7.v
module eje7 (
    input wire clk,
    input wire reset,
    input wire A,  // Cambiado a entrada
    input wire B,  // Cambiado a entrada
    input wire C,
    input wire D,
    output wire F2,
    output wire F2_optimizada,
    output wire y,  // Salida correcta
    output wire y_optimizada, // Salida correcta
    output wire z,
    output wire z_optimizada

);

    // Operación lógica para la salida
    assign F2 = ~A&~B&C | ~A&B&C | A&~B;
    assign F2_optimizada = ~A&C | A&~B;

    assign y = ~A&D | A&~C&D | A&~B&C | A&B&C&D;
    assign y_optimizada = D&(~A | A&(~C | B&C)) | A&~B&C;

    assign z = B&D | A&~C&D;
    assign z_optimizada = D&(B|A&~C);



endmodule

Guia2/Ejercicio 7/eje7_tb.v
`default_nettype none
`timescale 100 ns / 10 ns

module eje7_tb();

//-- Parámetro para definir cuánto dura la simulación
parameter DURATION = 100; // Cambiá esto según lo que necesites

//-- Señales de entrada del módulo
reg clk = 0;
reg reset;
reg A;  // Cambiado a reg para poder asignar valores
reg B;  // Cambiado a reg para poder asignar valores
reg C;
reg D;

wire y;  // Salida correcta
wire y_optimizada; // Salida correcta

wire z;
wire z_optimizada;

wire F2;
wire F2_optimizada;

//-- Instanciación del módulo bajo prueba
eje7 UUT (
    .clk(clk),
    .reset(reset),
    .A(A),
    .B(B),
    .C(C),
    .D(D)
);
integer n;

//-- Bloque inicial: estímulos y configuración
initial begin
  // Archivo para almacenar la traza
  $dumpfile("eje7_tb.vcd");
  $dumpvars(0, eje7_tb);
  reset = 1;
  #1;
  reset = 0;
  for (n = 0; n < 16; n = n + 1) begin
    {A,B,C,D}=n;
    #1; // Esperar un ciclo de reloj
  end


  // Finalizar simulación
  #(DURATION) $display("Fin de la simulación");
  $finish;
end

endmodule

Guia2/Ejercicio 7/eje7_tb.vcd
$date
	Sun May 11 12:55:51 2025
$end
$version
	Icarus Verilog
$end
$timescale
	1ps
$end
$scope module eje7_tb $end
$var parameter 32 ! DURATION $end
$var reg 1 " A $end
$var reg 1 # B $end
$var reg 1 $ C $end
$var reg 1 % D $end
$var reg 1 & clk $end
$var reg 1 ' reset $end
$var integer 32 ( n [31:0] $end
$scope module UUT $end
$var wire 1 " A $end
$var wire 1 # B $end
$var wire 1 $ C $end
$var wire 1 % D $end
$var wire 1 ) F2 $end
$var wire 1 * F2_optimizada $end
$var wire 1 & clk $end
$var wire 1 ' reset $end
$var wire 1 + y $end
$var wire 1 , y_optimizada $end
$var wire 1 - z $end
$var wire 1 . z_optimizada $end
$upscope $end
$upscope $end
$enddefinitions $end
$comment Show the parameter values. $end
$dumpall
b1100100 !
$end
#0
$dumpvars
x.
x-
x,
x+
x*
x)
bx (
1'
0&
x%
x$
x#
x"
$end
#100000
0+
0)
0*
0,
0-
0.
0"
0#
0$
0%
b0 (
0'
#200000
1+
1,
1%
b1 (
#300000
0+
1)
1*
0,
1$
0%
b10 (
#400000
1+
1,
1%
b11 (
#500000
0+
0)
0*
0,
1#
0$
0%
b100 (
#600000
1+
1,
1-
1.
1%
b101 (
#700000
0+
1)
1*
0,
0-
0.
1$
0%
b110 (
#800000
1+
1,
1-
1.
1%
b111 (
#900000
0+
0,
0-
0.
1"
0#
0$
0%
b1000 (
#1000000
1+
1,
1-
1.
1%
b1001 (
#1100000
0-
0.
1$
0%
b1010 (
#1200000
1%
b1011 (
#1300000
0)
0*
0+
0,
1#
0$
0%
b1100 (
#1400000
1+
1,
1-
1.
1%
b1101 (
#1500000
0+
0,
0-
0.
1$
0%
b1110 (
#1600000
1+
1,
1-
1.
1%
b1111 (
#1700000
b10000 (
