Guia3/eje3/c/ejercicio3c.v
module ejercicio3c (
    input wire clk,
    input wire reset,
    output reg [2:0] salidas,  // Cambiado a entrada
    input wire [7:0] entradas
);

    // Operación lógica para la salida
    always @(*) begin
            casez (entradas)
                8'b1???????: salidas = 3'b111;
                8'b01??????: salidas = 3'b110; // 0
                8'b001?????: salidas = 3'b101; // 1
                8'b0001????: salidas = 3'b100; // 2
                8'b00001???: salidas = 3'b011; // 3
                8'b000001??: salidas = 3'b010; // 4
                8'b0000001?: salidas = 3'b001; // 5
                8'b00000001: salidas = 3'b000; // 6
                8'b00000000: salidas = 3'bxxx;
                default: salidas = 3'bxxx; // Valor por defecto
            endcase
    end

endmodule

Guia3/eje3/c/ejercicio3c_tb.v
`default_nettype none
`timescale 100 ns / 10 ns

module ejercicio3c_tb();

//-- Parámetro para definir cuánto dura la simulación
parameter DURATION = 100; // Cambiá esto según lo que necesites

//-- Señales de entrada del módulo
reg clk = 0;
reg reset;

input wire [2:0] salida_tb;
reg [7:0] entrada_tb;
//-- Instanciación del módulo bajo prueba
ejercicio3c UUT (
    .clk(clk),
    .reset(reset),
    .entradas(entrada_tb),
    .salidas(salida_tb)
);

//-- Bloque inicial: estímulos y configuración
initial begin
  // Archivo para almacenar la traza
  $dumpfile("ejercicio3c_tb.vcd");
  $dumpvars(0, ejercicio3c_tb);
  reset = 1;
  #1;
  reset = 0;
  entrada_tb = 8'b00000000; // Valor inicial de entrada
  #1;
  entrada_tb = 8'b00000001; // Cambiar entrada a 1
  #1;
  entrada_tb = 8'b00000010; // Cambiar entrada a 2
  #1;
  entrada_tb = 8'b00000100; // Cambiar entrada a 3
  #1;
  entrada_tb = 8'b00001000; // Cambiar entrada a 4
  #1;
  entrada_tb = 8'b00010000; // Cambiar entrada a 5
  #1;
  entrada_tb = 8'b00100000; // Cambiar entrada a 6
  #1;
  entrada_tb = 8'b01000000; // Cambiar entrada a 7
  #1;
  entrada_tb = 8'b10000000; // Cambiar entrada a 8
  #1;
  entrada_tb = 8'bxxxxxxxx; // Cambiar entrada a 0
  #1;
  entrada_tb = 8'b00011111; // Cambiar entrada a 0 nuevamente
  // Finalizar simulación
  #(DURATION) $display("Fin de la simulación");
  $finish;
end

endmodule

Guia3/eje3/c/ejercicio3c_tb.vcd
$date
	Fri May 30 11:25:30 2025
$end
$version
	Icarus Verilog
$end
$timescale
	1ps
$end
$scope module ejercicio3c_tb $end
$var wire 3 ! salida_tb [2:0] $end
$var parameter 32 " DURATION $end
$var reg 1 # clk $end
$var reg 8 $ entrada_tb [7:0] $end
$var reg 1 % reset $end
$scope module UUT $end
$var wire 1 # clk $end
$var wire 8 & entradas [7:0] $end
$var wire 1 % reset $end
$var reg 3 ' salidas [2:0] $end
$upscope $end
$upscope $end
$enddefinitions $end
$comment Show the parameter values. $end
$dumpall
b1100100 "
$end
#0
$dumpvars
bx '
bx &
1%
bx $
0#
bx !
$end
#100000
b0 $
b0 &
0%
#200000
b0 !
b0 '
b1 $
b1 &
#300000
b1 !
b1 '
b10 $
b10 &
#400000
b10 !
b10 '
b100 $
b100 &
#500000
b11 !
b11 '
b1000 $
b1000 &
#600000
b100 !
b100 '
b10000 $
b10000 &
#700000
b101 !
b101 '
b100000 $
b100000 &
#800000
b110 !
b110 '
b1000000 $
b1000000 &
#900000
b111 !
b111 '
b10000000 $
b10000000 &
#1000000
bx !
bx '
bx $
bx &
#1100000
b100 !
b100 '
b11111 $
b11111 &
