Guia3/eje4/ejercicio4.v
module ejercicio4a (
    input wire clk,
    input wire reset,
    input wire [3:0]bin_nat,
    output reg [3:0]BCD
);
always @(*) begin
    if (bin_nat<=4'd9)
        BCD = bin_nat;
    else
        BCD = 4'bXXXX;
end

endmodule


module ejercicio4b (
    input wire clk,
    input wire reset,
    input wire [3:0]bin_nat,
    output reg [3:0]Gray
);

always @(*) begin
    if (bin_nat <= 4'd9) begin
        Gray[3] = bin_nat[3];
        Gray[2] = bin_nat[3] ^ bin_nat[2];
        Gray[1] = bin_nat[2] ^ bin_nat[1];
        Gray[0] = bin_nat[1] ^ bin_nat[0];
    end else begin
        Gray = 4'bXXXX; // Valor no válido
    end
end

endmodule

module ejercicio4c (
    input wire clk,
    input wire reset,
    input wire [3:0]bin_nat,
    output wire [6:0]hamming_code
);
    assign hamming_code[6] = bin_nat[3] ^ bin_nat[2] ^ bin_nat[0]; //p1 = d1 ^ d2 ^ d4
    assign hamming_code[5] = bin_nat[3] ^ bin_nat[1] ^ bin_nat[0]; // p2 = d1 ^ d3 ^ d4
    assign hamming_code[3] = bin_nat[2] ^ bin_nat[1] ^ bin_nat[0]; // p3 = d2 ^ d3 ^ d4
    assign hamming_code[0] = bin_nat[0]; // d1 = b0
    assign hamming_code[1] = bin_nat[1]; // d2 = b1
    assign hamming_code[2] = bin_nat[2]; // d3 = b2
    assign hamming_code[4] = bin_nat[3]; // d4 = b3
    //p1 p2 d1 p3 d2 d3 d4   =  hamming_code[6:0]

endmodule

Guia3/eje4/ejercicio4_tb.v
`default_nettype none
`timescale 100 ns / 10 ns

module ejercicio4_tb();

//-- Parámetro para definir cuánto dura la simulación
parameter DURATION = 100; // Cambiá esto según lo que necesites

//-- Señales de entrada del módulo
reg clk = 0;
reg reset;
output reg [3:0]bin_nat_tb;
input wire [3:0]BCD_tb;
input wire [3:0]Gray_tb;
input wire [6:0]hamming_code_tb;
//-- Instanciación del módulo bajo prueba
ejercicio4a UUT (
    .clk(clk),
    .reset(reset),
    .bin_nat(bin_nat_tb),
    .BCD(BCD_tb)
);

ejercicio4b UUT2 (
    .clk(clk),
    .reset(reset),
    .bin_nat(bin_nat_tb),
    .Gray(Gray_tb)
);
ejercicio4c UUT3 (
    .clk(clk),
    .reset(reset),
    .bin_nat(bin_nat_tb),
    .hamming_code(hamming_code_tb)
);

integer i;
//-- Bloque inicial: estímulos y configuración
initial begin
  // Archivo para almacenar la traza
  $dumpfile("ejercicio4_tb.vcd");
  $dumpvars(0, ejercicio4_tb);
  reset = 1;
  #1;
  reset = 0;
  for( i = 0; i < 16; i = i + 1) begin
    #1;
    bin_nat_tb = i[3:0];
  end

  // Finalizar simulación
  #(DURATION) $display("Fin de la simulación");
  $finish;
end

endmodule

Guia3/eje4/ejercicio4_tb.vcd
$date
	Fri May 30 15:42:10 2025
$end
$version
	Icarus Verilog
$end
$timescale
	1ps
$end
$scope module ejercicio4_tb $end
$var wire 7 ! hamming_code_tb [6:0] $end
$var wire 4 " Gray_tb [3:0] $end
$var wire 4 # BCD_tb [3:0] $end
$var parameter 32 $ DURATION $end
$var reg 4 % bin_nat_tb [3:0] $end
$var reg 1 & clk $end
$var reg 1 ' reset $end
$var integer 32 ( i [31:0] $end
$scope module UUT $end
$var wire 4 ) bin_nat [3:0] $end
$var wire 1 & clk $end
$var wire 1 ' reset $end
$var reg 4 * BCD [3:0] $end
$upscope $end
$scope module UUT2 $end
$var wire 4 + bin_nat [3:0] $end
$var wire 1 & clk $end
$var wire 1 ' reset $end
$var reg 4 , Gray [3:0] $end
$upscope $end
$scope module UUT3 $end
$var wire 4 - bin_nat [3:0] $end
$var wire 1 & clk $end
$var wire 1 ' reset $end
$var wire 7 . hamming_code [6:0] $end
$upscope $end
$upscope $end
$enddefinitions $end
$comment Show the parameter values. $end
$dumpall
b1100100 $
$end
#0
$dumpvars
bx .
bx -
bx ,
bx +
bx *
bx )
bx (
1'
0&
bx %
bx #
bx "
bx !
$end
#100000
b0 (
0'
#200000
b0 "
b0 ,
b0 #
b0 *
b0 !
b0 .
b1 (
b0 %
b0 )
b0 +
b0 -
#300000
b1 #
b1 *
b1 "
b1 ,
b1101001 !
b1101001 .
b10 (
b1 %
b1 )
b1 +
b1 -
#400000
b11 "
b11 ,
b10 #
b10 *
b101010 !
b101010 .
b11 (
b10 %
b10 )
b10 +
b10 -
#500000
b11 #
b11 *
b10 "
b10 ,
b1000011 !
b1000011 .
b100 (
b11 %
b11 )
b11 +
b11 -
#600000
b110 "
b110 ,
b100 #
b100 *
b1001100 !
b1001100 .
b101 (
b100 %
b100 )
b100 +
b100 -
#700000
b101 #
b101 *
b111 "
b111 ,
b100101 !
b100101 .
b110 (
b101 %
b101 )
b101 +
b101 -
#800000
b101 "
b101 ,
b110 #
b110 *
b1100110 !
b1100110 .
b111 (
b110 %
b110 )
b110 +
b110 -
#900000
b111 #
b111 *
b100 "
b100 ,
b1111 !
b1111 .
b1000 (
b111 %
b111 )
b111 +
b111 -
#1000000
b1100 "
b1100 ,
b1000 #
b1000 *
b1110000 !
b1110000 .
b1001 (
b1000 %
b1000 )
b1000 +
b1000 -
#1100000
b1001 #
b1001 *
b1101 "
b1101 ,
b11001 !
b11001 .
b1010 (
b1001 %
b1001 )
b1001 +
b1001 -
#1200000
bx "
bx ,
bx #
bx *
b1011010 !
b1011010 .
b1011 (
b1010 %
b1010 )
b1010 +
b1010 -
#1300000
b110011 !
b110011 .
b1100 (
b1011 %
b1011 )
b1011 +
b1011 -
#1400000
b111100 !
b111100 .
b1101 (
b1100 %
b1100 )
b1100 +
b1100 -
#1500000
b1010101 !
b1010101 .
b1110 (
b1101 %
b1101 )
b1101 +
b1101 -
#1600000
b10110 !
b10110 .
b1111 (
b1110 %
b1110 )
b1110 +
b1110 -
#1700000
b1111111 !
b1111111 .
b10000 (
b1111 %
b1111 )
b1111 +
b1111 -
