Guia3/eje3/b/ejercicio3b.v
module ejercicio3b (
    input wire clk,
    input wire reset,
    output reg [9:0] salida,  // Cambiado a entrada
    input wire [3:0] entrada
);

    // Operación lógica para la salida
    always @(*) begin
        case (entrada)
            4'b0000: salida = 10'b0000000001; // 1
            4'b0001: salida = 10'b0000000010; // 2
            4'b0010: salida = 10'b0000000100; // 4
            4'b0011: salida = 10'b0000001000; // 8
            4'b0100: salida = 10'b0000010000; // 16
            4'b0101: salida = 10'b0000100000; // 32
            4'b0110: salida = 10'b0001000000; // 64
            4'b0111: salida = 10'b0010000000; // 128
            4'b1000: salida = 10'b0100000000; // 256
            4'b1001: salida = 10'b1000000000; // 512
            4'b1111: salida = 10'b0000000000; // Valor por defecto
            default: salida = 10'bxxxxxxxxxx; // Valor indefinido
        endcase
    end

endmodule

Guia3/eje3/b/ejercicio3b_tb.v
`default_nettype none
`timescale 100 ns / 10 ns

module ejercicio3b_tb();

//-- Parámetro para definir cuánto dura la simulación
parameter DURATION = 100; // Cambiá esto según lo que necesites

//-- Señales de entrada del módulo
reg clk = 0;
reg reset;

input wire [9:0] salida_tb;
reg [3:0] entrada_tb;
//-- Instanciación del módulo bajo prueba
ejercicio3b UUT (
    .clk(clk),
    .reset(reset),
    .entrada(entrada_tb),
    .salida(salida_tb)
);

//-- Bloque inicial: estímulos y configuración
initial begin
  // Archivo para almacenar la traza
  $dumpfile("ejercicio3b_tb.vcd");
  $dumpvars(0, ejercicio3b_tb);
  reset = 1;
  #1;
  reset = 0;
  entrada_tb = 4'b0000; // Valor inicial de entrada
  #1
  entrada_tb = 4'b0001; // Cambiar entrada a 1
  #1
  entrada_tb = 4'b0010; // Cambiar entrada a 2
  #1
  entrada_tb = 4'b0011; // Cambiar entrada a 3
  #1
  entrada_tb = 4'b0100; // Cambiar entrada a 4
  #1
  entrada_tb = 4'b0101; // Cambiar entrada a 5
  #1
  entrada_tb = 4'b0110; // Cambiar entrada a 6
  #1
  entrada_tb = 4'b0111; // Cambiar entrada a 7
  #1
  entrada_tb = 4'b1000; // Cambiar entrada a 8
  #1
  entrada_tb = 4'b1001; // Cambiar entrada a 9
  #1
  entrada_tb = 4'b1110; // Cambiar entrada a 15
  #1
  entrada_tb = 4'b1111; // Cambiar entrada a 15 (valor por defecto)
  // Finalizar simulación
  #(DURATION) $display("Fin de la simulación");
  $finish;
end

endmodule

Guia3/eje3/b/ejercicio3b_tb.vcd
$date
	Fri May 30 10:26:27 2025
$end
$version
	Icarus Verilog
$end
$timescale
	1ps
$end
$scope module ejercicio3b_tb $end
$var wire 10 ! salida_tb [9:0] $end
$var parameter 32 " DURATION $end
$var reg 1 # clk $end
$var reg 4 $ entrada_tb [3:0] $end
$var reg 1 % reset $end
$scope module UUT $end
$var wire 1 # clk $end
$var wire 4 & entrada [3:0] $end
$var wire 1 % reset $end
$var reg 10 ' salida [9:0] $end
$upscope $end
$upscope $end
$enddefinitions $end
$comment Show the parameter values. $end
$dumpall
b1100100 "
$end
#0
$dumpvars
bx '
bx &
1%
bx $
0#
bx !
$end
#100000
b1 !
b1 '
b0 $
b0 &
0%
#200000
b10 !
b10 '
b1 $
b1 &
#300000
b100 !
b100 '
b10 $
b10 &
#400000
b1000 !
b1000 '
b11 $
b11 &
#500000
b10000 !
b10000 '
b100 $
b100 &
#600000
b100000 !
b100000 '
b101 $
b101 &
#700000
b1000000 !
b1000000 '
b110 $
b110 &
#800000
b10000000 !
b10000000 '
b111 $
b111 &
#900000
b100000000 !
b100000000 '
b1000 $
b1000 &
#1000000
b1000000000 !
b1000000000 '
b1001 $
b1001 &
#1100000
bx !
bx '
b1110 $
b1110 &
#1200000
b0 !
b0 '
b1111 $
b1111 &
